eaiesbinternscalcdemo/__init__.py
eaiesbinternscalcdemo-0.1.dist-info/LICENCE.txt
eaiesbinternscalcdemo-0.1.dist-info/METADATA
eaiesbinternscalcdemo-0.1.dist-info/WHEEL
eaiesbinternscalcdemo-0.1.dist-info/top_level.txt
eaiesbinternscalcdemo-0.1.dist-info/RECORD
