Metadata-Version: 2.1
Name: eaiesbinternscalcdemo
Version: 0.1
Summary: Basic calculator demo for interns
Home-page: UNKNOWN
Author: Abhilash
Author-email: abhilash.durgam@eaiesb.com
License: UNKNOWN
Platform: UNKNOWN
Classifier: Programming Language :: Python :: 3
Classifier: License :: OSI Approved :: MIT License
Classifier: Operating System :: OS Independent
License-File: LICENCE.txt
